pandas_image_methods/__init__.py
pandas_image_methods/core.py
pandas_image_methods/dask.py
pandas_image_methods/huggingface.py
pandas_image_methods-0.3.3.dist-info/LICENSE
pandas_image_methods-0.3.3.dist-info/METADATA
pandas_image_methods-0.3.3.dist-info/WHEEL
pandas_image_methods-0.3.3.dist-info/RECORD
