Metadata-Version: 2.1
Name: pandas-image-methods
Version: 0.3.3
Summary: Image methods for pandas dataframes using Pillow
License: Apache-2.0
Author: Quentin Lhoest
Requires-Python: >=3.10
Classifier: License :: OSI Approved :: Apache Software License
Classifier: Programming Language :: Python :: 3
Classifier: Programming Language :: Python :: 3.10
Classifier: Programming Language :: Python :: 3.11
Classifier: Programming Language :: Python :: 3.12
Classifier: Programming Language :: Python :: 3.13
Requires-Dist: numpy (>=2.0)
Requires-Dist: pandas (>=2.0)
Requires-Dist: pillow (>=9)
Requires-Dist: pyarrow (>=0.18)
